[{"company_fund":35691},{"emp":{"1":{"name":"Rakib","rank":"A","address":"Halishahor","mobile":"0192314496","bank_account":{"account_type":"current","account_name":"A1111","account_number":"Ac1111","current_balance":3888.5,"your_salary":3388.5,"bank":"uttora","branch_name":"Halishahor"}}},"0":{"basic":2510}},{"emp":{"1":{"name":"Abir","rank":"B","address":"Halishahor","mobile":"0192314497","bank_account":{"account_type":"current","account_name":"A22221","account_number":"Ac2221","current_balance":2913.5,"your_salary":2713.5,"bank":"uttora","branch_name":"Halishahor"}}},"0":{"basic":2010}},{"emp":{"1":{"name":"Abir khan","rank":"C","address":"Halishahor","mobile":"0192314497","bank_account":{"account_type":"current","account_name":"A22221","account_number":"Ac2221","current_balance":2438.5,"your_salary":2038.5,"bank":"uttora","branch_name":"Halishahor"}},"2":{"name":"iman","rank":"C","address":"Halishahor","mobile":"0192314497","bank_account":{"account_type":"current","account_name":"A22221","account_number":"Ac2221","current_balance":2438.5,"your_salary":2038.5,"bank":"uttora","branch_name":"Halishahor"}}},"0":{"basic":1510}},{"emp":{"1":{"name":"Toky","rank":"D","address":"Halishahor","mobile":"0192314497","bank_account":{"account_type":"current","account_name":"A22221","account_number":"Ac2221","current_balance":1763.5,"your_salary":1363.5,"bank":"uttora","branch_name":"Halishahor"}},"2":{"name":"SHamim","rank":"D","address":"Halishahor","mobile":"0192314497","bank_account":{"account_type":"current","account_name":"A22221","account_number":"Ac2221","current_balance":1763.5,"your_salary":1363.5,"bank":"uttora","branch_name":"Halishahor"}}},"0":{"basic":1010}},{"emp":{"1":{"name":"Omar","rank":"E","address":"Halishahor","mobile":"0192314497","bank_account":{"account_type":"current","account_name":"A22221","account_number":"Ac2221","current_balance":1088.5,"your_salary":688.5,"bank":"uttora","branch_name":"Halishahor"}},"2":{"name":"Hasib","rank":"E","address":"Halishahor","mobile":"0192314497","bank_account":{"account_type":"current","account_name":"A22221","account_number":"Ac2221","current_balance":1088.5,"your_salary":688.5,"bank":"uttora","branch_name":"Halishahor"}}},"0":{"basic":510}},{"emp":{"1":{"name":"Sakil","rank":"F","address":"Halishahor","mobile":"0192314497","bank_account":{"account_type":"current","account_name":"A22221","account_number":"Ac2221","current_balance":428.5,"your_salary":13.5,"bank":"uttora","branch_name":"Halishahor"}},"2":{"name":"Rafi","rank":"F","address":"Halishahor","mobile":"0192314497","bank_account":{"account_type":"current","account_name":"A22221","account_number":"Ac2221","current_balance":413.5,"your_salary":13.5,"bank":"uttora","branch_name":"Halishahor"}}},"0":{"basic":"10"}}]